Workbook

Sheet 1 - Cover
A1: Cover Page | E1: Date : | G1: 46157 | J1: Unilever PLC Financial Modelling
E2: Author : | G2: Nideesh Chandrasekar
A5: CONTENTS
C6: Assumptions and Notes | E6: 2
C7: Income Statement | E7: 3
C8: Balance Sheet | E8: 4
C9: Cashflow Statement | E9: 5
C10: Supporting Schedules | E10: 6
A14: SUMMARY
C15: This document is a three-statement financial model for Unilever PLC that analyses the company’s past financial performance from 2021–2025 and forecasts its future performance from 2026–2030. It includes projected income statements, balance sheets, and cash flow statements, along with key assumptions such as revenue growth, operating costs, taxes, and capital spending. The model is designed to evaluate Unilever’s financial position, profitability, and future business performance in a simple and structured way.
M40: Page : | N40: 1

Sheet 2 - Assumptions and Notes
A1: Assumptions and Notes | E1: Date : | G1: 46157 | J1: Unilever PLC Financial Modelling
E2: Author : | G2: Nideesh Chandrasekar
D4: Historical Data | I4: Forecasted Years
A5: Key Forecasting Assumptions
A6: Fiscal Year | D6: 2021 | E6: 2022 | F6: 2023 | G6: 2024 | H6: 2025 | I6: 2026 | J6: 2027 | K6: 2028 | L6: 2029 | M6: 2030
A8: Revenue Growth | D8: NA | E8: =('3 - Income Statement'!E8/'3 - Income Statement'!D8) - 1 -> 0.077651198 | F8: =('3 - Income Statement'!F8/'3 - Income Statement'!E8) - 1 -> -0.11301982 | G8: =('3 - Income Statement'!G8/'3 - Income Statement'!F8) - 1 -> -0.047129962 | H8: =('3 - Income Statement'!H8/'3 - Income Statement'!G8) - 1 -> 0.091343855 | I8: 0.041 | J8: 0.041 | K8: 0.041 | L8: 0.041 | M8: 0.041
A9: COGS as a % of Revenue | D9: ='3 - Income Statement'!D9/'3 - Income Statement'!D8 * -1 -> 0.57698107 | E9: ='3 - Income Statement'!E9/'3 - Income Statement'!E8 * -1 -> 0.5977054 | F9: ='3 - Income Statement'!F9/'3 - Income Statement'!F8 * -1 -> 0.56463062 | G9: ='3 - Income Statement'!G9/'3 - Income Statement'!G8 * -1 -> 0.53308502 | H9: ='3 - Income Statement'!H9/'3 - Income Statement'!H8 * -1 -> 0.53054001 | I9: 0.56 | J9: 0.56 | K9: 0.56 | L9: 0.56 | M9: 0.56
A10: Operating Cost as a % of Rev | D10: ='3 - Income Statement'!D11/'3 - Income Statement'!D8 * -1 -> 0.23926621 | E10: ='3 - Income Statement'!E11/'3 - Income Statement'!E8 * -1 -> 0.24395336 | F10: ='3 - Income Statement'!F11/'3 - Income Statement'!F8 * -1 -> 0.25590045 | G10: ='3 - Income Statement'!G11/'3 - Income Statement'!G8 * -1 -> 0.27105912 | H10: ='3 - Income Statement'!H11/'3 - Income Statement'!H8 * -1 -> 0.26893245 | I10: 0.256 | J10: 0.256 | K10: 0.256 | L10: 0.256 | M10: 0.256
A11: D&A as a % of PP&E | D11: ='6 - Supporting Schedules'!D18/'6 - Supporting Schedules'!D16 -> 0.16874846 | E11: ='6 - Supporting Schedules'!E18/'6 - Supporting Schedules'!E16 -> 0.14773373 | F11: ='6 - Supporting Schedules'!F18/'6 - Supporting Schedules'!F16 -> 0.099086069 | G11: ='6 - Supporting Schedules'!G18/'6 - Supporting Schedules'!G16 -> 0.083751305 | H11: ='6 - Supporting Schedules'!H18/'6 - Supporting Schedules'!H16 -> 0.10337333 | I11: 0.12 | J11: 0.12 | K11: 0.12 | L11: 0.12 | M11: 0.12
A12: Interest as a % of Debt | D12: ='3 - Income Statement'!D14/'6 - Supporting Schedules'!D25 * -1 -> 0.015797674 | E12: ='3 - Income Statement'!E14/'6 - Supporting Schedules'!E25 * -1 -> 0.024825519 | F12: ='3 - Income Statement'!F14/'6 - Supporting Schedules'!F25 * -1 -> 0.030888721 | G12: ='3 - Income Statement'!G14/'6 - Supporting Schedules'!G25 * -1 -> 0.029759372 | H12: ='3 - Income Statement'!H14/'6 - Supporting Schedules'!H25 * -1 -> 0.039490926 | I12: 0.028 | J12: 0.028 | K12: 0.028 | L12: 0.028 | M12: 0.028
A13: Tax Rate (% of EBT) | D13: ='3 - Income Statement'!D17/'3 - Income Statement'!D16 * -1 -> 0.22613375 | E13: ='3 - Income Statement'!E17/'3 - Income Statement'!E16 * -1 -> 0.20011022 | F13: ='3 - Income Statement'!F17/'3 - Income Statement'!F16 * -1 -> 0.23069008 | G13: ='3 - Income Statement'!G17/'3 - Income Statement'!G16 * -1 -> 0.27860421 | H13: ='3 - Income Statement'!H17/'3 - Income Statement'!H16 * -1 -> 0.28537304 | I13: 0.246 | J13: 0.246 | K13: 0.246 | L13: 0.246 | M13: 0.246
A14: Accounts Receivable (Days | D14: =('4 - Balance Sheet'!D10/'3 - Income Statement'!D8) *365 -> 31.346951 | E14: =('4 - Balance Sheet'!E10/'3 - Income Statement'!E8) *365 -> 34.499238 | F14: =('4 - Balance Sheet'!F10/'3 - Income Statement'!F8) *365 -> 38.35011 | G14: =('4 - Balance Sheet'!G10/'3 - Income Statement'!G8) *365 -> 36.041451 | H14: =('4 - Balance Sheet'!H10/'3 - Income Statement'!H8) *365 -> 41.513121 | I14: 36.2 | J14: 36.2 | K14: 36.2 | L14: 36.2 | M14: 36.2
A15: Inventory (Days) | D15: =('6 - Supporting Schedules'!D10/'3 - Income Statement'!D9) * 365 * -1 -> 56.489155 | E15: =('6 - Supporting Schedules'!E10/'3 - Income Statement'!E9) * 365 * -1 -> 60.291255 | F15: =('6 - Supporting Schedules'!F10/'3 - Income Statement'!F9) * 365 * -1 -> 64.031072 | G15: =('6 - Supporting Schedules'!G10/'3 - Income Statement'!G9) * 365 * -1 -> 67.543709 | H15: =('6 - Supporting Schedules'!H10/'3 - Income Statement'!H9) * 365 * -1 -> 55.075831 | I15: 61 | J15: 61 | K15: 61 | L15: 61 | M15: 61
A16: Accounts Payable (Days) | D16: =('4 - Balance Sheet'!D19/'3 - Income Statement'!D9) * 365 *-1 -> 107.3083 | E16: =('4 - Balance Sheet'!E19/'3 - Income Statement'!E9) * 365 *-1 -> 112.83582 | F16: =('4 - Balance Sheet'!F19/'3 - Income Statement'!F9) * 365 *-1 -> 129.52486 | G16: =('4 - Balance Sheet'!G19/'3 - Income Statement'!G9) * 365 *-1 -> 133.8343 | H16: =('4 - Balance Sheet'!H19/'3 - Income Statement'!H9) * 365 *-1 -> 149.76503 | I16: 145 | J16: 140 | K16: 135 | L16: 130 | M16: 125 | N16: 1
A17: CapEx (as a % of Rev) | D17: ='5 - Cashflow Statement'!D16/'3 - Income Statement'!D8 * -1 -> 0.021127492 | E17: ='5 - Cashflow Statement'!E16/'3 - Income Statement'!E8 * -1 -> 0.024237855 | F17: ='5 - Cashflow Statement'!F16/'3 - Income Statement'!F8 * -1 -> 0.023104022 | G17: ='5 - Cashflow Statement'!G16/'3 - Income Statement'!G8 * -1 -> 0.026314241 | H17: ='5 - Cashflow Statement'!H16/'3 - Income Statement'!H8 * -1 -> 0.028057372 | I17: 0.024 | J17: 0.024 | K17: 0.024 | L17: 0.024 | M17: 0.024
A18: Debt Issuance (Repayment) | D18: ='6 - Supporting Schedules'!D23+'6 - Supporting Schedules'!D24 -> 1582.1 | E18: ='6 - Supporting Schedules'!E23+'6 - Supporting Schedules'!E24 -> -1849.2 | F18: ='6 - Supporting Schedules'!F23+'6 - Supporting Schedules'!F24 -> 102.7 | G18: ='6 - Supporting Schedules'!G23+'6 - Supporting Schedules'!G24 -> 643.4 | H18: ='6 - Supporting Schedules'!H23+'6 - Supporting Schedules'!H24 -> -2112.4 | I18: -326.68 | J18: -326.68 | K18: -326.68 | L18: -326.68 | M18: -326.68
A19: Equity Issued | D19: 0 | E19: 0 | F19: 0 | G19: 0 | H19: 0 | I19: 0 | J19: 0 | K19: 0 | L19: 0 | M19: 0
A20: Equity Repurchased | D20: -3435 | E20: -1615.8 | F20: -1663.7 | G20: -1562.2 | H20: -1774 | I20: -2010.14 | J20: -2010.14 | K20: -2010.14 | L20: -2010.14 | M20: -2010.14
A21: Days in Period | D21: 365 | E21: 365 | F21: 365 | G21: 365 | H21: 365 | I21: 365 | J21: 365 | K21: 365 | L21: 365 | M21: 365
A27: Notes
A28: 1 | B28: Unilever has conceded to breashing payment code and has been confirmed 'too slow' in paying their suppliers
M41: Page : | N41: 2

Sheet 3 - Income Statement
A1: Income Statement | E1: Date : | G1: 46157 | J1: Unilever PLC Financial Modelling
E2: Author : | G2: Nideesh Chandrasekar
D4: Historical Data | I4: Forecasted Years
A5: INCOME Statement
A6: Fiscal Year | D6: 2021 | E6: 2022 | F6: 2023 | G6: 2024 | H6: 2025 | I6: 2026 | J6: 2027 | K6: 2028 | L6: 2029 | M6: 2030
A8: Revenue | D8: 59690 | E8: 64325 | F8: 57055 | G8: 54366 | H8: 59332 | I8: =H8+H8*'2 - Assumptions and Notes'!I8 -> 61764.612 | J8: =I8+I8*'2 - Assumptions and Notes'!J8 -> 64296.961 | K8: =J8+J8*'2 - Assumptions and Notes'!K8 -> 66933.136 | L8: =K8+K8*'2 - Assumptions and Notes'!L8 -> 69677.395 | M8: =L8+L8*'2 - Assumptions and Notes'!M8 -> 72534.168
A9: Cost of Goods Sold (COGS) | D9: -34440 | E9: -38447.4 | F9: -32215 | G9: -28981.7 | H9: -31478 | I9: ='2 - Assumptions and Notes'!I9*'3 - Income Statement'!I8*-1 -> -34588.183 | J9: ='2 - Assumptions and Notes'!J9*'3 - Income Statement'!J8*-1 -> -36006.298 | K9: ='2 - Assumptions and Notes'!K9*'3 - Income Statement'!K8*-1 -> -37482.556 | L9: ='2 - Assumptions and Notes'!L9*'3 - Income Statement'!L8*-1 -> -39019.341 | M9: ='2 - Assumptions and Notes'!M9*'3 - Income Statement'!M8*-1 -> -40619.134
A10: Gross Profit | D10: =D8+D9 -> 25250 | E10: =E8+E9 -> 25877.6 | F10: =F8+F9 -> 24840 | G10: =G8+G9 -> 25384.3 | H10: =H8+H9 -> 27854 | I10: =I8+I9 -> 27176.429 | J10: =J8+J9 -> 28290.663 | K10: =K8+K9 -> 29450.58 | ... M10: =M8+M9 -> 31915.034
A11: Total Operating Expenses | D11: -14281.8 | E11: -15692.3 | F11: -14600.4 | G11: -14736.4 | H11: -15956.3 | I11: =-1*'2 - Assumptions and Notes'!I10*'3 - Income Statement'!I8 -> -15811.741 | J11: =-1*'2 - Assumptions and Notes'!J10*'3 - Income Statement'!J8 -> -16460.022 | K11: =-1*'2 - Assumptions and Notes'!K10*'3 - Income Statement'!K8 -> -17134.883 | L11: =-1*'2 - Assumptions and Notes'!L10*'3 - Income Statement'!L8 -> -17837.413 | M11: =-1*'2 - Assumptions and Notes'!M10*'3 - Income Statement'!M8 -> -18568.747
A12: Operating Income | D12: =D10+D11 -> 10968.2 | E12: =E10+E11 -> 10185.3 | F12: =F10+F11 -> 10239.6 | G12: =G10+G11 -> 10647.9 | H12: =H10+H11 -> 11897.7 | I12: =I10+I11 -> 11364.689 | J12: =J10+J11 -> 11830.641 | K12: =K10+K11 -> 12315.697 | ... M12: =M10+M11 -> 13346.287
A14: Interest Expense | D14: -566.8 | E14: -844.8 | F14: -1054.3 | G14: -1034.9 | H14: -1289.9
A15: Net Interest and Other Expenses | D15: -1230.6 | E15: 883.6 | F15: -716 | G15: -1976.1 | H15: -1683 | I15: =-1.7% * I8 -> -1049.9984 | J15: =-1.7% * J8 -> -1093.0483 | K15: =-1.7% * K8 -> -1137.8633 | L15: =-1.7% * L8 -> -1184.5157 | M15: =-1.7% * M8 -> -1233.0809
A16: Pretax Profit (EBT) | D16: =D12+D15 -> 9737.6 | E16: =E12+E15 -> 11068.9 | F16: =F12+F15 -> 9523.6 | G16: =G12+G15 -> 8671.8 | H16: =H12+H15 -> 10214.7 | I16: =I12+I15 -> 10314.69 | J16: =J12+J15 -> 10737.593 | K16: =K12+K15 -> 11177.834 | ... M16: =M12+M15 -> 12113.206
A17: Tax Expense | D17: -2202 | E17: -2215 | F17: -2197 | G17: -2416 | H17: -2915 | I17: ='2 - Assumptions and Notes'!I13*I16*-1 -> -2537.4138 | J17: ='2 - Assumptions and Notes'!J13*J16*-1 -> -2641.4478 | K17: ='2 - Assumptions and Notes'!K13*K16*-1 -> -2749.7471 | L17: ='2 - Assumptions and Notes'!L13*L16*-1 -> -2862.4867 | M17: ='2 - Assumptions and Notes'!M13*M16*-1 -> -2979.8487
A18: Net Earnings from Continued Operations | D18: =D16+D17 -> 7535.6 | E18: =E16+E17 -> 8853.9 | F18: =F16+F17 -> 7326.6 | G18: =G16+G17 -> 6255.8 | H18: =H16+H17 -> 7299.7 | I18: =I16+I17 -> 7777.2764 | J18: =J16+J17 -> 8096.1447 | K18: =K16+K17 -> 8428.0867 | ... M18: =M16+M17 -> 9133.3574
A20: Earnings from Discontinued Operations and Other | D20: -651 | E20: -671 | F20: -165 | G20: -306 | H20: 3825 | I20: =0.75% * I8 * -1 -> -463.23459 | J20: =0.75% * J8 * -1 -> -482.22721 | K20: =0.75% * K8 * -1 -> -501.99852 | L20: =0.75% * L8 * -1 -> -522.58046 | M20: =0.75% * M8 * -1 -> -544.00626 | N20: 1
A21: Net Income | D21: =D18+D20 -> 6884.6 | E21: =E18+E20 -> 8182.9 | F21: =F18+F20 -> 7161.6 | G21: =G18+G20 -> 5949.8 | H21: =H18+H20 -> 11124.7 | I21: =I18+I20 -> 7314.0418 | J21: =J18+J20 -> 7613.9175 | K21: =K18+K20 -> 7926.0882 | ... M21: =M18+M20 -> 8589.3511
A25: Notes
A26: 1 | B26: Earnings from Discontinued Operations in 2025 is abnormal presumably due to one time sale of assets or equity.
M40: Page : | N40: 1

Sheet 4 - Balance Sheet
A1: Balance Sheet | E1: Date : | G1: 46157 | J1: Unilever PLC Financial Modelling
E2: Author : | G2: Nideesh Chandrasekar
D4: Historical Data | I4: Forecasted Years
A5: Balance Sheet
A6: Fiscal Year | D6: 2021 | E6: 2022 | F6: 2023 | G6: 2024 | H6: 2025 | I6: 2026 | J6: 2027 | K6: 2028 | L6: 2029 | M6: 2030
A8: Assets
A9: Total Cash & ST Investments | D9: 5128.6 | E9: 5994.2 | F9: 6744.3 | G9: 7581.1 | H9: 5888.2 | I9: =(I21+I27)-I10-I11-I12-I15 -> 6123.1922 | J9: =(J21+J27)-J10-J11-J12-J15 -> 5911.3015 | K9: =(K21+K27)-K10-K11-K12-K15 -> 5917.9088 | L9: =(L21+L27)-L10-L11-L12-L15 -> 6156.8234 | M9: =(M21+M27)-M10-M11-M12-M15 -> 6641.7053
A10: Accounts Receivables | D10: 5126.3 | E10: 6079.9 | F10: 5994.7 | G10: 5368.3 | H10: 6748.1 | I10: ='3 - Income Statement'!I8*'2 - Assumptions and Notes'!I14/'2 - Assumptions and Notes'!I21 -> 6125.6958 | J10: ='3 - Income Statement'!J8*'2 - Assumptions and Notes'!J14/'2 - Assumptions and Notes'!J21 -> 6376.8493 | K10: ='3 - Income Statement'!K8*'2 - Assumptions and Notes'!K14/'2 - Assumptions and Notes'!K21 -> 6638.3001 | L10: ='3 - Income Statement'!L8*'2 - Assumptions and Notes'!L14/'2 - Assumptions and Notes'!L21 -> 6910.4704 | M10: ='3 - Income Statement'!M8*'2 - Assumptions and Notes'!M14/'2 - Assumptions and Notes'!M21 -> 7193.7997 | N10: 1
A11: Inventory | D11: 5330.1 | E11: 6350.8 | F11: 5651.4 | G11: 5363.1 | H11: 4749.8 | I11: ='3 - Income Statement'!I9* -1 * '2 - Assumptions and Notes'!I15/'2 - Assumptions and Notes'!I21 -> 5780.4908 | J11: ='3 - Income Statement'!J9*-1*'2 - Assumptions and Notes'!J15/'2 - Assumptions and Notes'!J21 -> 6017.4909 | K11: ='3 - Income Statement'!K9*-1*'2 - Assumptions and Notes'!K15/'2 - Assumptions and Notes'!K21 -> 6264.2081 | L11: ='3 - Income Statement'!L9*-1*'2 - Assumptions and Notes'!L15/'2 - Assumptions and Notes'!L21 -> 6521.0406 | M11: ='3 - Income Statement'!M9*-1*'2 - Assumptions and Notes'!M15/'2 - Assumptions and Notes'!M21 -> 6788.4033 | N11: 2
A12: Prepaid Expenses and Other CA | D12: 4220.4 | E12: 2088 | F12: 1373.4 | G12: 1571.5 | H12: 2663.3 | I12: =H12*('3 - Income Statement'!I9/'3 - Income Statement'!H9) -> 2926.4473 | J12: =I12*('3 - Income Statement'!J9/'3 - Income Statement'!I9) -> 3046.4316 | K12: =J12*('3 - Income Statement'!K9/'3 - Income Statement'!J9) -> 3171.3353 | L12: =K12*('3 - Income Statement'!L9/'3 - Income Statement'!K9) -> 3301.36 | M12: =L12*('3 - Income Statement'!M9/'3 - Income Statement'!L9) -> 3436.7158
A13: Total Current Assets | D13: =SUM(D9:D12) -> 19805.4 | E13: =SUM(E9:E12) -> 20512.9 | F13: =SUM(F9:F12) -> 19763.8 | G13: =SUM(G9:G12) -> 19884 | H13: =SUM(H9:H12) -> 20049.4 | I13: =SUM(I9:I12) -> 20955.826 | J13: =SUM(J9:J12) -> 21352.073 | K13: =SUM(K9:K12) -> 21991.752 | ... M13: =SUM(M9:M12) -> 24060.624
A15: PP&E and other Long Term Assets | D15: 65665.8 | E15: 62816.2 | F15: 63329.6 | G15: 62732.8 | H15: 62740.8 | I15: ='6 - Supporting Schedules'!I19+50749.6 -> 62784.207 | J15: ='6 - Supporting Schedules'!J19+50749.6 -> 62883.181 | K15: ='6 - Supporting Schedules'!K19+50749.6 -> 63033.547 | L15: ='6 - Supporting Schedules'!L19+50749.6 -> 63231.73 | M15: ='6 - Supporting Schedules'!M19+50749.6 -> 63474.695
A16: Total Assets | D16: =D13+D15 -> 85471.2 | E16: =E13+E15 -> 83329.1 | F16: =F13+F15 -> 83093.4 | G16: =G13+G15 -> 82616.8 | H16: =H13+H15 -> 82790.2 | I16: =I13+I15 -> 83740.033 | J16: =J13+J15 -> 84235.254 | K16: =K13+K15 -> 85025.299 | ... M16: =M13+M15 -> 87535.319
A18: Liabilities
A19: Accounts Payable | D19: 10125.2 | E19: 11885.6 | F19: 11431.9 | G19: 10626.7 | H19: 12915.9 | I19: ='3 - Income Statement'!I9*-1*'2 - Assumptions and Notes'!I16/'2 - Assumptions and Notes'!I21 -> 13740.511 | J19: ='3 - Income Statement'!J9*-1*'2 - Assumptions and Notes'!J16/'2 - Assumptions and Notes'!J21 -> 13810.635 | K19: ='3 - Income Statement'!K9*-1*'2 - Assumptions and Notes'!K16/'2 - Assumptions and Notes'!K21 -> 13863.411 | L19: ='3 - Income Statement'!L9*-1*'2 - Assumptions and Notes'!L16/'2 - Assumptions and Notes'!L21 -> 13897.3 | M19: ='3 - Income Statement'!M9*-1*'2 - Assumptions and Notes'!M16/'2 - Assumptions and Notes'!M21 -> 13910.662 | N19: 3
A20: Total Debt and Other | D20: 42746.4 | E20: 36320.9 | F20: 37306.2 | G20: 37997.6 | H20: 36297 | I20: ='6 - Supporting Schedules'!I25+15991.5 -> 48886.22 | J20: ='6 - Supporting Schedules'!J25+15991.5 -> 48559.54 | K20: ='6 - Supporting Schedules'!K25+15991.5 -> 48232.86 | L20: ='6 - Supporting Schedules'!L25+15991.5 -> 47906.18 | M20: ='6 - Supporting Schedules'!M25+15991.5 -> 47579.5
A21: Total Liabilities | D21: 62996.8 | E21: 60092.1 | F21: 60170 | G21: 59251 | H21: 62128.8 | I21: =I19+I20 -> 62626.731 | J21: =J19+J20 -> 62370.175 | K21: =K19+K20 -> 62096.271 | L21: =L19+L20 -> 61803.48 | M21: =M19+M20 -> 61490.162
A23: Equity
A24: Total Equity | D24: -33733.2 | E24: -33442.6 | F24: -31960.6 | G24: -30799.7 | H24: -33715.9 | I24: =H27+'3 - Income Statement'!I21+(-4852)+(-2010.14) -> 21113.302 | J24: =I24+'3 - Income Statement'!J21+(-4852)+(-2010.14) -> 21865.079 | K24: =J24+'3 - Income Statement'!K21+(-4852)+(-2010.14) -> 22929.028 | L24: =K24+'3 - Income Statement'!L21+(-4852)+(-2010.14) -> 24317.945 | M24: =L24+'3 - Income Statement'!M21+(-4852)+(-2010.14) -> 26045.156
A25: Retained Earnings | D25: 53204 | E25: 53809.8 | F25: 51945.2 | G25: 51508.3 | H25: 51960.8
A26: Minority Interest | D26: 3004 | E26: 2870 | F26: 2939 | G26: 2657 | H26: 2416.5
A27: Stockholder Equity | D27: =SUM(D24:D26) -> 22474.8 | E27: =SUM(E24:E26) -> 23237.2 | F27: =SUM(F24:F26) -> 22923.6 | G27: =SUM(G24:G26) -> 23365.6 | H27: =SUM(H24:H26) -> 20661.4 | I27: =I24 -> 21113.302 | J27: =J24 -> 21865.079 | K27: =K24 -> 22929.028 | L27: =L24 -> 24317.945 | M27: =M24 -> 26045.156
A29: Balance Check | D29: =D16-D21-D27 -> -0.4 | E29: =E16-E21-E27 -> -0.2 | F29: =F16-F21-F27 -> -0.2 | G29: =G16-G21-G27 -> 0.2 | H29: =H16-H21-H27 -> 0 | I29: =I16-I21-I27 -> 0 | J29: =J16-J21-J27 -> 0 | K29: =K16-K21-K27 -> 0 | ... M29: =M16-M21-M27 -> 0
A32: Notes
A33: 1 | B33: AR Days held flat at 36.2 days (5-year historical average) for all forecast years
A34: 2 | B34: Inventory Days forecast at 61 days for all forecast years, reflecting Unilever active inventory reduction programme
A35: 3 | B35: AP Days declining from 145 in 2026 to 125 in 2030 (5 day reduction per year), mean reverting toward historical average from unsustainable 2025 peak of 150 days
M40: Page : | N40: 1

Sheet 5 - Cashflow Statement
A1: Cashflow Statement | E1: Date : | G1: 46157 | J1: Unilever PLC Financial Modelling
E2: Author : | G2: Nideesh Chandrasekar
D4: Historical Data | I4: Forecasted Years
A5: Cashflow Statement
A6: Fiscal Year | D6: 2021 | E6: 2022 | F6: 2023 | G6: 2024 | H6: 2025 | I6: 2026 | J6: 2027 | K6: 2028 | L6: 2029 | M6: 2030
A8: Net Income | D8: 6884.8 | E8: 8182.9 | F8: 7161.6 | G8: 5950.5 | H8: 11124.3 | I8: ='3 - Income Statement'!I21 -> 7314.0418 | J8: ='3 - Income Statement'!J21 -> 7613.9175 | K8: ='3 - Income Statement'!K21 -> 7926.0882 | L8: ='3 - Income Statement'!L21 -> 8251.0578 | M8: ='3 - Income Statement'!M21 -> 8589.3511
A9: Depreciation & Amortization, Total | D9: 1987.3 | E9: 1847.1 | F9: 1267.4 | G9: 1067 | H9: 1279.4 | I9: ='6 - Supporting Schedules'!I18 -> 1438.944 | J9: ='6 - Supporting Schedules'!J18 -> 1444.1528 | K9: ='6 - Supporting Schedules'!K18 -> 1456.0297 | L9: ='6 - Supporting Schedules'!L18 -> 1474.0736 | M9: ='6 - Supporting Schedules'!M18 -> 1497.8556
A10: Other Operating Activities | D10: 575.8 | E10: -1532.4 | F10: 232.9 | G10: 1994.2 | H10: -3073.4 | I10: -360.58 | J10: -360.58 | K10: -360.58 | L10: -360.58 | M10: -360.58
A11: Change In Accounts Receivable | D11: -349.4 | E11: -1983.1 | F11: 807 | G11: -218.6 | H11: -3078 | I11: ='4 - Balance Sheet'!I10-'4 - Balance Sheet'!H10 -> -622.40423 | J11: ='4 - Balance Sheet'!J10-'4 - Balance Sheet'!I10 -> 251.15353 | K11: ='4 - Balance Sheet'!K10-'4 - Balance Sheet'!J10 -> 261.45082 | L11: ='4 - Balance Sheet'!L10-'4 - Balance Sheet'!K10 -> 272.1703 | M11: ='4 - Balance Sheet'!M10-'4 - Balance Sheet'!L10 -> 283.32929
A12: Change In Inventories | D12: -521.3 | E12: -1496.9 | F12: 311.3 | G12: -196.8 | H12: -330.1 | I12: ='4 - Balance Sheet'!I11-'4 - Balance Sheet'!H11 -> 1030.6908 | J12: ='4 - Balance Sheet'!J11-'4 - Balance Sheet'!I11 -> 237.00012 | K12: ='4 - Balance Sheet'!K11-'4 - Balance Sheet'!J11 -> 246.71713 | L12: ='4 - Balance Sheet'!L11-'4 - Balance Sheet'!K11 -> 256.83253 | M12: ='4 - Balance Sheet'!M11-'4 - Balance Sheet'!L11 -> 267.36266
A13: Change In Accounts Payable | D13: 817.2 | E13: 3028.2 | F13: -287 | G13: 220.7 | H13: 3544.4 | I13: ='4 - Balance Sheet'!I19-'4 - Balance Sheet'!H19 -> 824.61094 | J13: ='4 - Balance Sheet'!J19-'4 - Balance Sheet'!I19 -> 70.123987 | K13: ='4 - Balance Sheet'!K19-'4 - Balance Sheet'!J19 -> 52.776355 | L13: ='4 - Balance Sheet'!L19-'4 - Balance Sheet'!K19 -> 33.888339 | M13: ='4 - Balance Sheet'!M19-'4 - Balance Sheet'!L19 -> 13.362788
A14: CFO (calculated from above) | D14: =SUM(D8:D13) -> 9394.4 | E14: =SUM(E8:E13) -> 8045.8 | F14: =SUM(F8:F13) -> 9493.2 | G14: =SUM(G8:G13) -> 8817 | H14: =SUM(H8:H13) -> 9466.6 | I14: =SUM(I8:I13) -> 9625.3033 | J14: =SUM(J8:J13) -> 9255.768 | K14: =SUM(K8:K13) -> 9582.4822 | ... M14: =SUM(M8:M13) -> 10290.682
A16: Capital Expenditure | D16: -1261.1 | E16: -1559.1 | F16: -1318.2 | G16: -1430.6 | H16: -1664.7 | I16: =-'2 - Assumptions and Notes'!I17*'3 - Income Statement'!I8 -> -1482.3507 | J16: =-'2 - Assumptions and Notes'!J17*'3 - Income Statement'!J8 -> -1543.1271 | K16: =-'2 - Assumptions and Notes'!K17*'3 - Income Statement'!K8 -> -1606.3953 | L16: =-'2 - Assumptions and Notes'!L17*'3 - Income Statement'!L8 -> -1672.2575 | M16: =-'2 - Assumptions and Notes'!M17*'3 - Income Statement'!M8 -> -1740.82
A17: Other Investing Activities | D17: -2433.4 | E17: 4185.6 | F17: -1214.5 | G17: 783.1 | H17: -1998.4 | I17: -135.52 | J17: -135.52 | K17: -135.52 | L17: -135.52 | M17: -135.52
A18: CFI | D18: =D17+D16 -> -3694.5 | E18: =E17+E16 -> 2626.5 | F18: =F17+F16 -> -2532.7 | G18: =G17+G16 -> -647.5 | H18: =H17+H16 -> -3663.1 | I18: =I16+I17 -> -1617.8707 | J18: =J16+J17 -> -1678.6471 | K18: =K16+K17 -> -1741.9153 | L18: =L16+L17 -> -1807.7775 | M18: =M16+M17 -> -1876.34
A20: Total Debt Issued | D20: 6150.7 | E20: 8326.4 | F20: 4877.5 | G20: 4981.9 | H20: 5025.8 | I20: ='6 - Supporting Schedules'!I23 -> 5872.46 | J20: ='6 - Supporting Schedules'!J23 -> 5872.46 | K20: ='6 - Supporting Schedules'!K23 -> 5872.46 | L20: ='6 - Supporting Schedules'!L23 -> 5872.46 | M20: ='6 - Supporting Schedules'!M23 -> 5872.46
A21: Total Debt Repaid | D21: -4568.6 | E21: -10175.6 | F21: -4774.8 | G21: -4338.5 | H21: -7138.2 | I21: ='6 - Supporting Schedules'!I24 -> -6199.14 | J21: ='6 - Supporting Schedules'!J24 -> -6199.14 | K21: ='6 - Supporting Schedules'!K24 -> -6199.14 | L21: ='6 - Supporting Schedules'!L24 -> -6199.14 | M21: ='6 - Supporting Schedules'!M24 -> -6199.14
A22: Other Financing Activities | D22: -9661.9 | E22: -7670 | F22: -8043.7 | G22: -7833.9 | H22: -5892.9 | I22: -6862.14 | J22: -6862.14 | K22: -6862.14 | L22: -6862.14 | M22: -6862.14
A23: CFF | D23: =D20+D21+D22 -> -8079.8 | E23: =E20+E21+E22 -> -9519.2 | F23: =F20+F21+F22 -> -7941 | G23: =G20+G21+G22 -> -7190.5 | H23: =H20+H21+H22 -> -8005.3 | I23: =I20+I21+I22 -> -7188.82 | J23: =J20+J21+J22 -> -7188.82 | K23: =K20+K21+K22 -> -7188.82 | ... M23: =M20+M21+M22 -> -7188.82
A25: Net change in Cash | D25: =D14+D18+D23 -> -2379.9 | E25: =E14+E18+E23 -> 1153.1 | F25: =F14+F18+F23 -> -980.5 | G25: =G14+G18+G23 -> 979 | H25: =H14+H18+H23 -> -2201.8 | I25: =I14+I18+I23 -> 818.61266 | J25: =J14+J18+J23 -> 388.30091 | K25: =K14+K18+K23 -> 651.7469 | ... M25: =M14+M18+M23 -> 1225.5215
A26: Opening Cash Balance | D26: 0 | E26: =D27 -> 5128.6 | F26: =E27 -> 6281.7 | G26: =F27 -> 5301.2 | H26: =G27 -> 6280.2 | I26: =H27 -> 4078.4 | J26: =I27 -> 4897.0127 | K26: =J27 -> 5285.3136 | L26: =K27 -> 5937.0605 | M26: =L27 -> 6867.9055
A27: Closing Cash Balance | D27: ='4 - Balance Sheet'!D9 -> 5128.6 | E27: =E25+E26 -> 6281.7 | F27: =F25+F26 -> 5301.2 | G27: =G25+G26 -> 6280.2 | H27: =H25+H26 -> 4078.4 | I27: =I25+I26 -> 4897.0127 | J27: =J25+J26 -> 5285.3136 | K27: =K25+K26 -> 5937.0605 | L27: =L25+L26 -> 6867.9055 | M27: =M25+M26 -> 8093.427
M40: Page : | N40: 1

Sheet 6 - Supporting Schedules
A1: Supporting Schedules | E1: Date : | G1: 46157 | J1: Unilever PLC Financial Modelling
E2: Author : | G2: Nideesh Chandrasekar
D4: Historical Data | I4: Forecasted Years
A5: Supporting Schedules
A6: Fiscal Year | D6: 2021 | E6: 2022 | F6: 2023 | G6: 2024 | H6: 2025 | I6: 2026 | J6: 2027 | K6: 2028 | L6: 2029 | M6: 2030
A8: Working Capital Schedule
A9: Accounts Receivable | D9: 5126.3 | E9: 6079.9 | F9: 5994.7 | G9: 5368.3 | H9: 6748.1 | I9: 6125.7 | J9: 6376.85 | K9: 6638.3 | L9: 6910.47 | M9: 7193.8
A10: Inventory | D10: 5330.1 | E10: 6350.8 | F10: 5651.4 | G10: 5363.1 | H10: 4749.8 | I10: 5780.49 | J10: 6017.49 | K10: 6264.21 | L10: 6521.04 | M10: 6788.4
A11: Accounts Payable | D11: 10125.2 | E11: 11885.6 | F11: 11431.9 | G11: 10626.7 | H11: 12915.9 | I11: 13740.51 | J11: 13810.63 | K11: 13863.41 | L11: 13897.3 | M11: 13910.66
A12: Net Working Capital (NWC) | D12: =D9+D10-D11 -> 331.2 | E12: =E9+E10-E11 -> 545.1 | F12: =F9+F10-F11 -> 214.2 | G12: =G9+G10-G11 -> 104.7 | H12: =H9+H10-H11 -> -1418
A13: Change in NWC | D13: NA | E13: =D12-E12 -> -213.9 | F13: =E12-F12 -> 330.9 | G13: =F12-G12 -> 109.5 | H13: =G12-H12 -> 1522.7
A15: Depreciation Schedule
A16: PPE Opening | D16: 11776.7 | E16: =D19 -> 12502.9 | F16: =E19 -> 12790.9 | G16: =F19 -> 12740.1 | H16: =G19 -> 12376.5 | I16: =H19 -> 11991.2 | J16: =I19 -> 12034.607 | K16: =J19 -> 12133.581 | L16: =K19 -> 12283.947 | M16: =L19 -> 12482.13
A17: Plus Capex | D17: -1261.1 | E17: -1559.1 | F17: -1318.2 | G17: -1430.6 | H17: -1664.7 | I17: ='3 - Income Statement'!I8*'2 - Assumptions and Notes'!I17 -> 1482.3507 | J17: ='3 - Income Statement'!J8*'2 - Assumptions and Notes'!J17 -> 1543.1271 | K17: ='3 - Income Statement'!K8*'2 - Assumptions and Notes'!K17 -> 1606.3953 | L17: ='3 - Income Statement'!L8*'2 - Assumptions and Notes'!L17 -> 1672.2575 | M17: ='3 - Income Statement'!M8*'2 - Assumptions and Notes'!M17 -> 1740.82
A18: Less Depreciation | D18: 1987.3 | E18: 1847.1 | F18: 1267.4 | G18: 1067 | H18: 1279.4 | I18: =I16*'2 - Assumptions and Notes'!I11 -> 1438.944 | J18: =J16*'2 - Assumptions and Notes'!J11 -> 1444.1528 | K18: =K16*'2 - Assumptions and Notes'!K11 -> 1456.0297 | L18: =L16*'2 - Assumptions and Notes'!L11 -> 1474.0736 | M18: =M16*'2 - Assumptions and Notes'!M11 -> 1497.8556
A19: PPE Closing | D19: =SUM(D16:D18) -> 12502.9 | E19: =SUM(E16:E18) -> 12790.9 | F19: =SUM(F16:F18) -> 12740.1 | G19: =SUM(G16:G18) -> 12376.5 | H19: =SUM(H16:H18) -> 11991.2 | I19: =I16+I17-I18 -> 12034.607 | J19: =J16+J17-J18 -> 12133.581 | K19: =K16+K17-K18 -> 12283.947 | L19: =L16+L17-L18 -> 12482.13 | M19: =M16+M17-M18 -> 12725.095
A21: Debt & Interest Schedule
A22: Debt Opening | D22: 34296.6 | E22: =D25 -> 35878.7 | F22: =E25 -> 34029.5 | G22: =F25 -> 34132.2 | H22: =G25 -> 34775.6 | I22: 33221.4 | J22: =I25 -> 32894.72 | K22: =J25 -> 32568.04 | L22: =K25 -> 32241.36 | M22: =L25 -> 31914.68
A23: Total Debt Issued | D23: 6150.7 | E23: 8326.4 | F23: 4877.5 | G23: 4981.9 | H23: 5025.8 | I23: 5872.46 | J23: 5872.46 | K23: 5872.46 | L23: 5872.46 | M23: 5872.46
A24: Total Debt Repaid | D24: -4568.6 | E24: -10175.6 | F24: -4774.8 | G24: -4338.5 | H24: -7138.2 | I24: -6199.14 | J24: -6199.14 | K24: -6199.14 | L24: -6199.14 | M24: -6199.14
A25: Debt Closing | D25: =SUM(D22:D24) -> 35878.7 | E25: =SUM(E22:E24) -> 34029.5 | F25: =SUM(F22:F24) -> 34132.2 | G25: =SUM(G22:G24) -> 34775.6 | H25: =SUM(H22:H24) -> 32663.2 | I25: =SUM(I22:I24) -> 32894.72 | J25: =SUM(J22:J24) -> 32568.04 | K25: =SUM(K22:K24) -> 32241.36 | ... M25: =SUM(M22:M24) -> 31588
A26: Interest Expense | D26: ='3 - Income Statement'!D15 -> -1230.6 | E26: ='3 - Income Statement'!E15 -> 883.6 | F26: ='3 - Income Statement'!F15 -> -716 | G26: ='3 - Income Statement'!G15 -> -1976.1 | H26: ='3 - Income Statement'!H15 -> -1683 | I26: -930.2 | J26: -921.05 | K26: -911.91 | L26: -902.76 | M26: -893.61
M40: Page : | N40: 1
