Workbook

Sheet DATA
A1: Sector | B1: Year | C1: PE Ratio | D1: EV/EBITDA | E1: Price-to-Book | F1: PEG Ratio | G1: ROIC | H1: FCF Yield | I1: Dividend Yield | J1: Payout Ratio | K1: Current Ratio | L1: ROE | M1: Debt/Equity | N1: Net Profit Margin | O1: Gross Margin | P1: Revenue Growth | Q1: Net Income Growth
A2: Basic Materials | B2: 2011 | C2: 11.195 | D2: 5.984 | E2: 1.411 | F2: 2.409 | G2: -0.03 | H2: -0.021 | I2: 0 | J2: 0 | K2: 2.391 | L2: -0.029 | M2: 0.002 | N2: 0.052 | O2: 0.389
A3: Basic Materials | B3: 2012 | C3: 16.232 | D3: 1.701 | E3: 1.381 | F3: 0.008 | G3: -0.044 | H3: -0.056 | I3: 0 | J3: 0 | K3: 2.279 | L3: -0.052 | M3: 0.038 | N3: 0.017 | O3: 0.34 | P3: -0.004 | Q3: -0.22
A4: Basic Materials | B4: 2013 | C4: 19.911 | D4: 0.618 | E4: 1.462 | F4: 0.019 | G4: -0.049 | H4: -0.028 | I4: 0 | J4: 0 | K4: 1.943 | L4: -0.05 | M4: 0.054 | N4: 0.028 | O4: 0.337 | P4: 0.019 | Q4: -0.095
A5: Basic Materials | B5: 2014 | C5: 26.213 | D5: 0.989 | E5: 1.61 | F5: 1.248 | G5: -0.04 | H5: -0.039 | I5: 0 | J5: 0 | K5: 1.999 | L5: -0.048 | M5: 0.047 | N5: 0.038 | O5: 0.328 | P5: 0.054 | Q5: -0.061
A6: Basic Materials | B6: 2015 | C6: 22.294 | D6: 0.065 | E6: 1.439 | F6: 0.035 | G6: -0.005 | H6: -0.029 | I6: 0 | J6: 0 | K6: 1.847 | L6: -0.019 | M6: 0.063 | N6: 0.035 | O6: 0.349 | P6: -0.06 | Q6: -0.032
A7: Basic Materials | B7: 2016 | C7: 18.319 | D7: 1.274 | E7: 1.407 | F7: 0.639 | G7: -0.006 | H7: -0.02 | I7: 0 | J7: 0 | K7: 1.943 | L7: 0 | M7: 0.048 | N7: 0.07 | O7: 0.344 | P7: 0.06 | Q7: -0.003
A8: Basic Materials | B8: 2017 | C8: 25.457 | D8: 2.076 | E8: 1.535 | F8: 0.005 | G8: -0.007 | H8: -0.017 | I8: 0 | J8: 0 | K8: 2.064 | L8: 0.002 | M8: 0.124 | N8: 0.05 | O8: 0.354 | P8: 0.186 | Q8: 0.052
A9: Basic Materials | B9: 2018 | C9: 23.088 | D9: 1.422 | E9: 1.406 | F9: 0.004 | G9: 0 | H9: -0.033 | I9: 0 | J9: 0 | K9: 2.03 | L9: -0.037 | M9: 0.084 | N9: 0.05 | O9: 0.372 | P9: 0.094 | Q9: 0.049
A10: Basic Materials | B10: 2019 | C10: 23.021 | D10: 0.645 | E10: 1.397 | F10: 32.101 | G10: 0.011 | H10: -0.027 | I10: 0 | J10: 0 | K10: 1.692 | L10: 0 | M10: 0.105 | N10: 0.049 | O10: 0.336 | P10: 0.04 | Q10: -0.078
A11: Basic Materials | B11: 2020 | C11: 32.641 | D11: 2.058 | E11: 1.551 | F11: 0.423 | G11: -0.008 | H11: -0.002 | I11: 0 | J11: 0 | K11: 2.09 | L11: -0.018 | M11: 0.112 | N11: 0.043 | O11: 0.326 | P11: -0.036 | Q11: -0.128
A12: Basic Materials | B12: 2021 | C12: 19.004 | D12: 0.907 | E12: 1.997 | F12: 0.005 | G12: -0.05 | H12: -0.026 | I12: 0 | J12: 0 | K12: 2.173 | L12: -0.01 | M12: 0.04 | N12: 0.082 | O12: 0.34 | P12: 0.269 | Q12: 0.323
A13: Basic Materials | B13: 2022 | C13: 19.825 | D13: 0.305 | E13: 1.131 | F13: 0.484 | G13: -0.017 | H13: -0.061 | I13: 0 | J13: 0 | K13: 1.9 | L13: -0.041 | M13: 0.084 | N13: 0.056 | O13: 0.367 | P13: 0.088 | Q13: -0.121
A14: Basic Materials | B14: 2023 | C14: 23.078 | D14: 7.241 | E14: 1.003 | F14: 0.25 | G14: -0.024 | H14: -0.089 | I14: 0 | J14: 0 | K14: 1.839 | L14: -0.033 | M14: 0.094 | N14: 0.026 | O14: 0.346 | P14: -0.057 | Q14: -0.235
... A16: Basic Materials | B16: 2025 | C16: 6.027 | D16: 5.06 | E16: 1.44 | F16: 1.096 | G16: 0.041 | H16: 0.03 | I16: 0 | J16: 0 | K16: 1.987 | L16: 0.022 | M16: 0.224 | N16: 0.032 | O16: 0.332 | P16: 0.015 | Q16: -0.123
A17: Basic Materials | B17: 2026 | D17: 8.415 | E17: 1.582 | F17: 0.262 | G17: -0.094 | H17: 0.05 | I17: 0.04 | J17: -1.344 | K17: 1.555 | L17: -0.048 | M17: 0.697 | N17: -0.008 | O17: 0.05 | P17: 0.077 | Q17: -1.257
A18: Communication Services | B18: 2011 | C18: 12.026 | D18: 7.169 | E18: 1.629 | F18: 2 | G18: 0.059 | H18: 0.03 | I18: 0.006 | J18: 0 | K18: 0.934 | L18: 0.055 | M18: 0.287 | N18: 0.036 | O18: 0.604
A19: Communication Services | B19: 2012 | C19: 13.462 | D19: 8.909 | E19: 1.825 | F19: 0.012 | G19: 0.084 | H19: 0.045 | I19: 0.014 | J19: 0.277 | K19: 0.996 | L19: 0.09 | M19: 0.242 | N19: 0.066 | O19: 0.546 | P19: 0.031 | Q19: 0.184
A20: Communication Services | B20: 2013 | C20: 15.454 | D20: 10.988 | E20: 2.353 | F20: 0.037 | G20: 0.093 | H20: 0.044 | I20: 0.008 | J20: 0.235 | K20: 1.006 | L20: 0.094 | M20: 0.026 | N20: 0.085 | O20: 0.48 | P20: 0.069 | Q20: 0.133
A21: Communication Services | B21: 2014 | C21: 11.579 | D21: 10.11 | E21: 2.237 | F21: 0.135 | G21: 0.061 | H21: 0.032 | I21: 0.012 | J21: 0.173 | K21: 0.998 | L21: 0.079 | M21: 0.065 | N21: 0.064 | O21: 0.455 | P21: 0.036 | Q21: 0.011
A22: Communication Services | B22: 2015 | C22: 13.055 | D22: 10.134 | E22: 2.549 | F22: 0.033 | G22: 0.07 | H22: 0.021 | I22: 0.009 | J22: 0.298 | K22: 1.097 | L22: 0.087 | M22: 0.222 | N22: 0.06 | O22: 0.423 | P22: 0.061 | Q22: 0.019
A23: Communication Services | B23: 2016 | C23: 16.823 | D23: 9.194 | E23: 1.862 | F23: 2.465 | G23: 0.057 | H23: 0.041 | I23: 0.015 | J23: 0.306 | K23: 1.114 | L23: 0.055 | M23: 0.165 | N23: 0.041 | O23: 0.432 | P23: 0.123 | Q23: -0.162
A24: Communication Services | B24: 2017 | C24: 13.543 | D24: 9.731 | E24: 1.69 | F24: 0.01 | G24: 0.065 | H24: 0.036 | I24: 0.011 | J24: 0.237 | K24: 1.325 | L24: 0.082 | M24: 0.142 | N24: 0.045 | O24: 0.476 | P24: 0.124 | Q24: 0.221
A25: Communication Services | B25: 2018 | C25: 13.169 | D25: 10.19 | E25: 1.708 | F25: 0.061 | G25: 0.064 | H25: 0.047 | I25: 0.01 | J25: 0.043 | K25: 1.232 | L25: 0.065 | M25: 0.213 | N25: 0.045 | O25: 0.451 | P25: 0.094 | Q25: 0.036
A26: Communication Services | B26: 2019 | C26: 8.99 | D26: 9.499 | E26: 2.055 | F26: 0.05 | G26: 0.059 | H26: 0.031 | I26: 0.008 | J26: 0 | K26: 1.399 | L26: 0.043 | M26: 0.309 | N26: 0.033 | O26: 0.445 | P26: 0.06 | Q26: 0.062
A27: Communication Services | B27: 2020 | C27: 35.435 | D27: 8.912 | E27: 2.068 | F27: 0.122 | G27: 0.023 | H27: 0.032 | I27: 0 | J27: 0 | K27: 1.345 | L27: -0.01 | M27: 0.399 | N27: -0.006 | O27: 0.357 | P27: -0.066 | Q27: -0.479
A28: Communication Services | B28: 2021 | C28: 11.468 | D28: 9.267 | E28: 2.99 | F28: 1.197 | G28: 0.046 | H28: 0.03 | I28: 0 | J28: 0 | K28: 1.293 | L28: 0.037 | M28: 0.304 | N28: 0.035 | O28: 0.391 | P28: 0.128 | Q28: -0.158
A29: Communication Services | B29: 2022 | C29: 12.731 | D29: 7.818 | E29: 1.786 | F29: 0.033 | G29: 0.05 | H29: 0.044 | I29: 0.004 | J29: 0.014 | K29: 1.322 | L29: 0.051 | M29: 0.276 | N29: 0.053 | O29: 0.41 | P29: 0.18 | Q29: 0.07
A30: Communication Services | B30: 2023 | C30: 10.168 | D30: 7.079 | E30: 1.597 | F30: 0.013 | G30: 0.053 | H30: 0.047 | I30: 0.007 | J30: 0.036 | K30: 1.322 | L30: 0.062 | M30: 0.13 | N30: 0.029 | O30: 0.394 | P30: 0.075 | Q30: -0.373
... A33: Communication Services | B33: 2026 | C33: 19.313 | D33: 5.375 | E33: 2.682 | F33: 0.122 | G33: 0.116 | H33: 0.127 | I33: 0.035 | J33: -0.512 | K33: 1.13 | L33: -0.008 | M33: 1.04 | N33: -0.01 | O33: 0.315 | P33: 0.07 | Q33: -0.904
A34: Consumer Cyclical | B34: 2011 | C34: 10.191 | D34: 5.902 | E34: 1.27 | F34: 0.177 | G34: 0.065 | H34: 0.032 | I34: 0.016 | J34: 0.175 | K34: 1.293 | L34: 0.102 | M34: 0.144 | N34: 0.056 | O34: 0.485
A35: Consumer Cyclical | B35: 2012 | C35: 11.305 | D35: 7.049 | E35: 1.578 | F35: 0.009 | G35: 0.086 | H35: 0.039 | I35: 0.019 | J35: 0.213 | K35: 1.364 | L35: 0.119 | M35: 0.14 | N35: 0.051 | O35: 0.431 | P35: 0.066 | Q35: 0.106
A36: Consumer Cyclical | B36: 2013 | C36: 13.983 | D36: 8.855 | E36: 1.905 | F36: 0.018 | G36: 0.079 | H36: 0.034 | I36: 0.014 | J36: 0.223 | K36: 1.28 | L36: 0.105 | M36: 0.168 | N36: 0.051 | O36: 0.379 | P36: 0.088 | Q36: 0.036
A37: Consumer Cyclical | B37: 2014 | C37: 14.543 | D37: 9.007 | E37: 2.412 | F37: 0.155 | G37: 0.085 | H37: 0.046 | I37: 0.016 | J37: 0.235 | K37: 1.241 | L37: 0.132 | M37: 0.314 | N37: 0.047 | O37: 0.379 | P37: 0.099 | Q37: 0.154
A38: Consumer Cyclical | B38: 2015 | C38: 13.549 | D38: 9.164 | E38: 2.575 | F38: 0.092 | G38: 0.102 | H38: 0.034 | I38: 0.015 | J38: 0.263 | K38: 1.3 | L38: 0.144 | M38: 0.301 | N38: 0.049 | O38: 0.372 | P38: 0.088 | Q38: 0.142
A39: Consumer Cyclical | B39: 2016 | C39: 15.271 | D39: 8.981 | E39: 2.482 | F39: 0.151 | G39: 0.093 | H39: 0.037 | I39: 0.02 | J39: 0.297 | K39: 1.309 | L39: 0.152 | M39: 0.287 | N39: 0.051 | O39: 0.386 | P39: 0.108 | Q39: 0.058
A40: Consumer Cyclical | B40: 2017 | C40: 14.763 | D40: 9.853 | E40: 2.367 | F40: 0.088 | G40: 0.093 | H40: 0.036 | I40: 0.019 | J40: 0.301 | K40: 1.309 | L40: 0.14 | M40: 0.269 | N40: 0.052 | O40: 0.399 | P40: 0.111 | Q40: 0.075
A41: Consumer Cyclical | B41: 2018 | C41: 13.267 | D41: 9.353 | E41: 2.127 | F41: 0.007 | G41: 0.086 | H41: 0.044 | I41: 0.024 | J41: 0.308 | K41: 1.254 | L41: 0.131 | M41: 0.315 | N41: 0.048 | O41: 0.378 | P41: 0.078 | Q41: -0.001
A42: Consumer Cyclical | B42: 2019 | C42: 12.387 | D42: 9.178 | E42: 1.924 | F42: 1.142 | G42: 0.078 | H42: 0.048 | I42: 0.02 | J42: 0.293 | K42: 1.279 | L42: 0.073 | M42: 0.448 | N42: 0.037 | O42: 0.374 | P42: 0.048 | Q42: -0.118
A43: Consumer Cyclical | B43: 2020 | C43: 11.888 | D43: 9.798 | E43: 1.757 | F43: 0.525 | G43: 0.034 | H43: 0.06 | I43: 0.002 | J43: 0 | K43: 1.265 | L43: 0.027 | M43: 0.67 | N43: 0.016 | O43: 0.328 | P43: -0.031 | Q43: -0.35
A44: Consumer Cyclical | B44: 2021 | C44: 12.045 | D44: 10.094 | E44: 2.261 | F44: 0.051 | G44: 0.058 | H44: 0.047 | I44: 0 | J44: 0 | K44: 1.42 | L44: 0.073 | M44: 0.594 | N44: 0.04 | O44: 0.325 | P44: 0.152 | Q44: -0.24
A45: Consumer Cyclical | B45: 2022 | C45: 9.742 | D45: 6.66 | E45: 1.551 | F45: 0.032 | G45: 0.068 | H45: 0.06 | I45: 0.009 | J45: 0.096 | K45: 1.374 | L45: 0.094 | M45: 0.752 | N45: 0.046 | O45: 0.358 | P45: 0.177 | Q45: 0.053
A46: Consumer Cyclical | B46: 2023 | C46: 11.292 | D46: 7.557 | E46: 1.566 | F46: 0.012 | G46: 0.051 | H46: 0.067 | I46: 0.019 | J46: 0.147 | K46: 1.284 | L46: 0.068 | M46: 0.698 | N46: 0.029 | O46: 0.381 | P46: 0.066 | Q46: -0.285
... A49: Consumer Cyclical | B49: 2026 | C49: 18.16 | D49: 6.051 | E49: 1.171 | F49: 0.443 | G49: 0.048 | H49: 0.179 | I49: 0.033 | J49: 0.473 | K49: 1.362 | L49: 0.065 | M49: 0.866 | N49: 0.026 | O49: 0.45 | P49: 0.014 | Q49: -0.142
A50: Consumer Defensive | B50: 2011 | C50: 14.088 | D50: 9.417 | E50: 3.281 | F50: 0.323 | G50: 0.113 | H50: 0.033 | I50: 0.024 | J50: 0.351 | K50: 1.35 | L50: 0.219 | M50: 0.439 | N50: 0.086 | O50: 0.387
A51: Consumer Defensive | B51: 2012 | C51: 15.99 | D51: 9.1 | E51: 2.504 | F51: 0.014 | G51: 0.108 | H51: 0.037 | I51: 0.026 | J51: 0.376 | K51: 1.197 | L51: 0.155 | M51: 0.458 | N51: 0.057 | O51: 0.326 | P51: 0.051 | Q51: 0.022
A52: Consumer Defensive | B52: 2013 | C52: 17.691 | D52: 12.519 | E52: 3.706 | F52: 0.097 | G52: 0.105 | H52: 0.032 | I52: 0.022 | J52: 0.413 | K52: 1.315 | L52: 0.196 | M52: 0.461 | N52: 0.054 | O52: 0.344 | P52: 0.024 | Q52: 0.02
A53: Consumer Defensive | B53: 2014 | C53: 18.455 | D53: 10.147 | E53: 3.398 | F53: 0.194 | G53: 0.112 | H53: 0.034 | I53: 0.021 | J53: 0.415 | K53: 1.323 | L53: 0.167 | M53: 0.42 | N53: 0.056 | O53: 0.346 | P53: -0.021 | Q53: 0.003
A54: Consumer Defensive | B54: 2015 | C54: 19.81 | D54: 13.6 | E54: 4.655 | F54: 0.076 | G54: 0.105 | H54: 0.036 | I54: 0.022 | J54: 0.437 | K54: 1.302 | L54: 0.189 | M54: 0.47 | N54: 0.055 | O54: 0.365 | P54: 0.001 | Q54: 0.062
A55: Consumer Defensive | B55: 2016 | C55: 23.306 | D55: 13.738 | E55: 3.519 | F55: 0.312 | G55: 0.095 | H55: 0.032 | I55: 0.018 | J55: 0.385 | K55: 1.37 | L55: 0.119 | M55: 0.305 | N55: 0.06 | O55: 0.379 | P55: 0.044 | Q55: 0.017
A56: Consumer Defensive | B56: 2017 | C56: 21.056 | D56: 12.526 | E56: 3.141 | F56: 0.175 | G56: 0.09 | H56: 0.035 | I56: 0.019 | J56: 0.298 | K56: 1.338 | L56: 0.15 | M56: 0.465 | N56: 0.061 | O56: 0.362 | P56: 0.146 | Q56: 0.157
A57: Consumer Defensive | B57: 2018 | C57: 19.085 | D57: 11.298 | E57: 3.004 | F57: 0.078 | G57: 0.078 | H57: 0.038 | I57: 0.022 | J57: 0.46 | K57: 1.396 | L57: 0.132 | M57: 0.396 | N57: 0.049 | O57: 0.355 | P57: 0.071 | Q57: 0.039
A58: Consumer Defensive | B58: 2019 | C58: 18.759 | D58: 9.442 | E58: 2.195 | F58: 1.425 | G58: 0.07 | H58: 0.036 | I58: 0.021 | J58: 0.377 | K58: 1.34 | L58: 0.096 | M58: 0.429 | N58: 0.044 | O58: 0.346 | P58: 0.027 | Q58: -0.022
A59: Consumer Defensive | B59: 2020 | C59: 14.04 | D59: 11.252 | E59: 2.472 | F59: 0.847 | G59: 0.05 | H59: 0.041 | I59: 0.019 | J59: 0.419 | K59: 1.379 | L59: 0.083 | M59: 0.439 | N59: 0.033 | O59: 0.344 | P59: -0.001 | Q59: -0.209
A60: Consumer Defensive | B60: 2021 | C60: 19.868 | D60: 9.762 | E60: 2.703 | F60: 0.036 | G60: 0.047 | H60: 0.039 | I60: 0.019 | J60: 0.41 | K60: 1.6 | L60: 0.092 | M60: 0.44 | N60: 0.053 | O60: 0.361 | P60: 0.093 | Q60: 0.033
A61: Consumer Defensive | B61: 2022 | C61: 14.523 | D61: 9.213 | E61: 2.324 | F61: 0.006 | G61: 0.063 | H61: 0.033 | I61: 0.03 | J61: 0.488 | K61: 1.572 | L61: 0.119 | M61: 0.433 | N61: 0.061 | O61: 0.347 | P61: 0.135 | Q61: -0.067
A62: Consumer Defensive | B62: 2023 | C62: 15.761 | D62: 9.443 | E62: 2.231 | F62: 0.01 | G62: 0.076 | H62: 0.057 | I62: 0.024 | J62: 0.33 | K62: 1.717 | L62: 0.099 | M62: 0.6 | N62: 0.053 | O62: 0.363 | P62: 0.052 | Q62: -0.24
... A65: Consumer Defensive | B65: 2026 | C65: 17.5 | D65: 8.748 | E65: 2.103 | F65: 0.986 | G65: 0.084 | H65: 0.076 | I65: 0.03 | J65: 0.524 | K65: 1.668 | L65: 0.139 | M65: 0.81 | N65: 0.048 | O65: 0.075 | P65: 0.054 | Q65: 0.179
A66: Energy | B66: 2011 | C66: 0.624 | D66: 1.038 | E66: 1.227 | F66: 2.765 | G66: -0.009 | H66: -0.017 | I66: 0 | J66: 0 | K66: 2.314 | L66: 0.024 | M66: 0 | N66: 0.067 | O66: 0.273
A67: Energy | B67: 2012 | C67: 16.85 | D67: 8.901 | E67: 1.232 | F67: 0 | G67: -0.025 | H67: -0.044 | I67: 0 | J67: 0 | K67: 2.162 | L67: -0.041 | M67: 0 | N67: 0.029 | O67: 0.301 | P67: 0.297 | Q67: -0.088
A68: Energy | B68: 2013 | C68: 27.261 | D68: 8.241 | E68: 1.378 | F68: 0.001 | G68: -0.025 | H68: -0.033 | I68: 0 | J68: 0 | K68: 2.168 | L68: -0.052 | M68: 0.04 | N68: 0.062 | O68: 0.261 | P68: 0.022 | Q68: -0.181
A69: Energy | B69: 2014 | C69: 39.838 | D69: 13.089 | E69: 1.217 | F69: 0.336 | G69: -0.05 | H69: -0.016 | I69: 0 | J69: 0 | K69: 2.865 | L69: -0.081 | M69: 0.009 | N69: 0.011 | O69: 0.258 | P69: -0.085 | Q69: -0.406
A70: Energy | B70: 2015 | C70: 24.241 | D70: 9.72 | E70: 0.882 | F70: 0.007 | G70: -0.067 | H70: -0.053 | I70: 0 | J70: 0 | K70: 3.588 | L70: -0.153 | M70: 0.004 | N70: -0.412 | O70: 0.121 | P70: -0.37 | Q70: -0.333
A71: Energy | B71: 2016 | C71: 20.846 | D71: 11.212 | E71: 1.218 | F71: 0.056 | G71: -0.048 | H71: -0.04 | I71: 0 | J71: 0 | K71: 3.376 | L71: -0.079 | M71: 0 | N71: -0.3 | O71: 0.114 | P71: -0.194 | Q71: -0.245
A72: Energy | B72: 2017 | C72: 23.177 | D72: 0.022 | E72: 1.288 | F72: 0.01 | G72: -0.037 | H72: -0.043 | I72: 0 | J72: 0 | K72: 3.196 | L72: -0.045 | M72: 0.006 | N72: -0.101 | O72: 0.118 | P72: 0.313 | Q72: -0.081
A73: Energy | B73: 2018 | C73: 18.934 | D73: 6.898 | E73: 1.123 | F73: 0.002 | G73: -0.044 | H73: -0.044 | I73: 0 | J73: 0 | K73: 1.741 | L73: -0.03 | M73: 0.062 | N73: -0.055 | O73: 0.325 | P73: 0.251 | Q73: -0.066
A74: Energy | B74: 2019 | C74: 23.193 | D74: 8.438 | E74: 0.869 | F74: 1.072 | G74: -0.021 | H74: -0.093 | I74: 0 | J74: 0 | K74: 1.825 | L74: -0.049 | M74: 0.064 | N74: -0.086 | O74: 0.295 | P74: -0.014 | Q74: -0.329
A75: Energy | B75: 2020 | C75: 23.091 | D75: 16.564 | E75: 0.901 | F75: 0.004 | G75: -0.064 | H75: -0.04 | I75: 0 | J75: 0 | K75: 1.417 | L75: -0.153 | M75: 0.093 | N75: -0.544 | O75: 0.109 | P75: -0.274 | Q75: -0.273
A76: Energy | B76: 2021 | C76: 28.434 | D76: 0.902 | E76: 0.848 | F76: 0.001 | G76: -0.026 | H76: -0.08 | I76: 0 | J76: 0 | K76: 1.614 | L76: -0.025 | M76: 0.109 | N76: -0.063 | O76: 0.364 | P76: 0.448 | Q76: -0.607
A77: Energy | B77: 2022 | C77: 18.495 | D77: 1.158 | E77: 0.991 | F77: 0.33 | G77: 0.002 | H77: 0.012 | I77: 0 | J77: 0 | K77: 1.424 | L77: -0.01 | M77: 0.145 | N77: 0.008 | O77: 0.514 | P77: 0.464 | Q77: -0.253
A78: Energy | B78: 2023 | C78: 10.747 | D78: 1.89 | E78: 0.787 | F78: 0.011 | G78: 0.001 | H78: -0.014 | I78: 0 | J78: 0 | K78: 1.414 | L78: -0.009 | M78: 0.118 | N78: 0.037 | O78: 0.405 | P78: -0.111 | Q78: -0.729
... A80: Energy | B80: 2025 | C80: 38.708 | D80: 2.437 | E80: 0.89 | F80: 0.047 | G80: -0.014 | H80: 0.043 | I80: 0 | J80: 0 | K80: 1.263 | L80: -0.028 | M80: 0.212 | N80: -0.029 | O80: 0.228 | P80: -0.078 | Q80: -0.856
A81: Financial Services | B81: 2011 | C81: 7.443 | D81: 19.591 | E81: 0.916 | F81: 0.024 | G81: 0.005 | H81: 0.007 | I81: 0.028 | J81: 0 | K81: 3.559 | L81: 0.02 | M81: 0 | N81: 0.113 | O81: 0.997
A82: Financial Services | B82: 2012 | C82: 6.99 | D82: 16.117 | E82: 0.949 | F82: 0 | G82: 0.048 | H82: 0.012 | I82: 0.02 | J82: 0.126 | K82: 3.435 | L82: 0.093 | M82: 0.002 | N82: 0.296 | O82: 1 | P82: 0.077 | Q82: -0.036
A83: Financial Services | B83: 2013 | C83: 9.705 | D83: 17.748 | E83: 0.961 | F83: 0 | G83: 0.068 | H83: 0.005 | I83: 0.022 | J83: 0.204 | K83: 6.173 | L83: 0.101 | M83: 0.001 | N83: 0.424 | O83: 1 | P83: 0.09 | Q83: 0.106
A84: Financial Services | B84: 2014 | C84: 12.032 | D84: 16.163 | E84: 0.979 | F84: 0.987 | G84: 0.055 | H84: 0.002 | I84: 0.023 | J84: 0.309 | K84: 6.65 | L84: 0.078 | M84: 0.002 | N84: 0.436 | O84: 1 | P84: -0.088 | Q84: -0.165
A85: Financial Services | B85: 2015 | C85: 9.587 | D85: 16.891 | E85: 1.029 | F85: 0.039 | G85: 0.038 | H85: 0.005 | I85: 0.025 | J85: 0.263 | K85: 5.597 | L85: 0.071 | M85: 0.002 | N85: 0.265 | O85: 0.999 | P85: 0.042 | Q85: 0.064
A86: Financial Services | B86: 2016 | C86: 8.609 | D86: 12.944 | E86: 0.947 | F86: 6.149 | G86: 0.073 | H86: 0.012 | I86: 0.028 | J86: 0.215 | K86: 4.995 | L86: 0.09 | M86: 0.001 | N86: 0.35 | O86: 0.928 | P86: 0.07 | Q86: -0.075
A87: Financial Services | B87: 2017 | C87: 10.974 | D87: 13.356 | E87: 0.973 | F87: 0.01 | G87: 0.049 | H87: 0.011 | I87: 0.029 | J87: 0.354 | K87: 6.544 | L87: 0.079 | M87: 0.001 | N87: 0.42 | O87: 0.921 | P87: 0.049 | Q87: -0.012
A88: Financial Services | B88: 2018 | C88: 11.099 | D88: 14.743 | E88: 0.965 | F88: 0.023 | G88: 0.027 | H88: 0.017 | I88: 0.034 | J88: 0.362 | K88: 5.103 | L88: 0.051 | M88: 0.011 | N88: 0.337 | O88: 0.892 | P88: 0.026 | Q88: -0.031
A89: Financial Services | B89: 2019 | C89: 6.416 | D89: 15.068 | E89: 0.939 | F89: 0.008 | G89: 0.012 | H89: 0.009 | I89: 0.034 | J89: 0.143 | K89: 3.823 | L89: 0.045 | M89: 0.038 | N89: 0.262 | O89: 0.895 | P89: -0.017 | Q89: -0.301
A90: Financial Services | B90: 2020 | C90: 6.894 | D90: 1.679 | E90: 0.931 | F90: 0.584 | G90: 0.055 | H90: 0.017 | I90: 0.024 | J90: 0.118 | K90: 3.322 | L90: 0.08 | M90: 0.041 | N90: 0.36 | O90: 0.928 | P90: -0.073 | Q90: -0.297
A91: Financial Services | B91: 2021 | C91: 6.589 | D91: 3.337 | E91: 0.966 | F91: 0.014 | G91: 0.08 | H91: 0.008 | I91: 0.033 | J91: 0.223 | K91: 4.212 | L91: 0.115 | M91: 0.041 | N91: 0.586 | O91: 0.933 | P91: 0.107 | Q91: 0.103
A92: Financial Services | B92: 2022 | C92: 4.379 | D92: 16.839 | E92: 0.901 | F92: 0 | G92: 0.017 | H92: 0.012 | I92: 0.042 | J92: 0 | K92: 4.282 | L92: 0.03 | M92: 0.04 | N92: 0.225 | O92: 0.872 | P92: -0.065 | Q92: -0.541
A93: Financial Services | B93: 2023 | C93: 6.738 | D93: 0.803 | E93: 0.885 | F93: 1.626 | G93: 0.025 | H93: 0.014 | I93: 0.039 | J93: 0.164 | K93: 3.314 | L93: 0.049 | M93: 0.041 | N93: 0.2 | O93: 0.907 | P93: 0.038 | Q93: -0.405
... A96: Financial Services | B96: 2026 | C96: 6.816 | D96: 9.656 | E96: 1.194 | F96: 1.409 | G96: 0.101 | H96: 0 | I96: 0.044 | J96: 0.325 | K96: 67.66 | L96: 0.174 | M96: 1.234 | N96: 6.471 | O96: 0.974 | P96: -0.538 | Q96: 0.056
A97: Healthcare | B97: 2011 | C97: 22.676 | D97: 4.488 | E97: 2.43 | F97: 0.035 | G97: 0.03 | H97: -0.019 | I97: 0 | J97: 0 | K97: 1.938 | L97: 0.025 | M97: 0.013 | N97: 0.029 | O97: 0.616
A98: Healthcare | B98: 2012 | C98: 24.983 | D98: 1.713 | E98: 2.48 | F98: 0.999 | G98: 0 | H98: -0.004 | I98: 0 | J98: 0 | K98: 2.217 | L98: 0.046 | M98: 0.028 | N98: 0.02 | O98: 0.56 | P98: 0.016 | Q98: 0.105
A99: Healthcare | B99: 2013 | C99: 23.718 | D99: 14.609 | E99: 3.055 | F99: 0.003 | G99: -0.119 | H99: -0.021 | I99: 0 | J99: 0 | K99: 2.055 | L99: -0.045 | M99: 0 | N99: -0.035 | O99: 0.564 | P99: 0.035 | Q99: -0.013
A100: Healthcare | B100: 2014 | C100: 27.583 | D100: 23.493 | E100: 2.79 | F100: 0 | G100: -0.083 | H100: -0.034 | I100: 0 | J100: 0 | K100: 2.348 | L100: -0.059 | M100: 0 | N100: -0.011 | O100: 0.616 | P100: 0.081 | Q100: 0.128
A101: Healthcare | B101: 2015 | C101: 25.647 | D101: 14.791 | E101: 3.719 | F101: 1.81 | G101: -0.093 | H101: 0 | I101: 0 | J101: 0 | K101: 2.615 | L101: 0 | M101: 0 | N101: -0.065 | O101: 0.581 | P101: 0.105 | Q101: 0.122
A102: Healthcare | B102: 2016 | C102: 39.021 | D102: 24.852 | E102: 3.67 | F102: 13.768 | G102: 0 | H102: 0 | I102: 0 | J102: 0 | K102: 2.853 | L102: 0.017 | M102: 0.005 | N102: 0.03 | O102: 0.543 | P102: 0.182 | Q102: -0.051
A103: Healthcare | B103: 2017 | C103: 35.634 | D103: 23.027 | E103: 3.355 | F103: 0.027 | G103: 0 | H103: -0.008 | I103: 0 | J103: 0 | K103: 2.34 | L103: -0.03 | M103: 0 | N103: -0.038 | O103: 0.564 | P103: 0.117 | Q103: -0.112
A104: Healthcare | B104: 2018 | C104: 38.724 | D104: 22.328 | E104: 3.34 | F104: 1.733 | G104: -0.011 | H104: -0.016 | I104: 0 | J104: 0 | K104: 2.602 | L104: 0.007 | M104: 0.016 | N104: 0 | O104: 0.613 | P104: 0.059 | Q104: -0.047
A105: Healthcare | B105: 2019 | C105: 48.699 | D105: 23.166 | E105: 3.32 | F105: 0.569 | G105: -0.152 | H105: -0.011 | I105: 0 | J105: 0 | K105: 2.596 | L105: 0.006 | M105: 0.049 | N105: -0.072 | O105: 0.526 | P105: 0.069 | Q105: -0.095
A106: Healthcare | B106: 2020 | C106: 42.236 | D106: 23.44 | E106: 4.152 | F106: 0.099 | G106: -0.039 | H106: -0.012 | I106: 0 | J106: 0 | K106: 3.027 | L106: -0.087 | M106: 0.1 | N106: -0.068 | O106: 0.576 | P106: 0.167 | Q106: 0.257
A107: Healthcare | B107: 2021 | C107: 41.927 | D107: 9.326 | E107: 3.322 | F107: 3.15 | G107: -0.026 | H107: -0.022 | I107: 0 | J107: 0 | K107: 3.506 | L107: -0.027 | M107: 0.041 | N107: -0.002 | O107: 0.566 | P107: 0.094 | Q107: 0.132
A108: Healthcare | B108: 2022 | C108: 58.016 | D108: 15.157 | E108: 2.362 | F108: 0.823 | G108: -0.014 | H108: -0.03 | I108: 0 | J108: 0 | K108: 2.338 | L108: -0.068 | M108: 0.145 | N108: 0.007 | O108: 0.552 | P108: 0.097 | Q108: -0.203
A109: Healthcare | B109: 2023 | C109: 45.107 | D109: 16.665 | E109: 2.304 | F109: 0.033 | G109: -0.136 | H109: -0.051 | I109: 0 | J109: 0 | K109: 2.324 | L109: -0.049 | M109: 0.065 | N109: -0.066 | O109: 0.541 | P109: 0.059 | Q109: -0.177
... A111: Healthcare | B111: 2025 | C111: 32.911 | D111: 13.245 | E111: 2.045 | F111: 0.105 | G111: -0.006 | H111: -0.015 | I111: 0 | J111: 0 | K111: 1.631 | L111: 0.047 | M111: 0.094 | N111: 0.01 | O111: 0.475 | P111: 0.088 | Q111: -0.062
...

Sheet CONTROL
B2: SECTOR MEDIANS | Interactive Dashboard Controls
B4: CHART 1: Metric Over Time (by Sector) | F4: CHART 2: All Sectors Snapshot (by Year)
B6: Select Sector: | C6: Basic Materials | F6: Select Year: | G6: 2024
B8: Select Metric: | C8: PE Ratio | F8: Select Metric: | G8: PE Ratio
B11: HOW TO USE:
B12: 1. Use the dropdowns above to select sector, year, and metric.
B13: 2. Navigate to the ACROSS_YEARS sheet to see the time-series line chart.
B14: 3. Navigate to the ACROSS_SECTORS sheet to see the sector comparison bar chart.
B15: 4. Charts update automatically when you change a selection above.
B17: Note: Charts are powered by helper tables on each chart sheet that use
B18: IFERROR/SUMPRODUCT formulas — no macros or VBA required.

Sheet ACROSS_YEARS
A1: Sector Medians Over Time
A3: → Change selections on CONTROL sheet to update this chart
A4: Sector: | B4: =CONTROL!C6 | C4: Metric: | D4: =CONTROL!C8
A7: Year | B7: Value
A8: 2011 | B8: =IFERROR(SUMPRODUCT((DATA!$A$2:$A$175=CONTROL!$C$6)*(DATA!$B$2:$B$175=2011)*INDEX(DATA!$C$2:$Q$175,0,MATCH(CONTROL!$C$8,DATA!$C$1:$Q$1,0))),"")
A9: 2012 | B9: =IFERROR(SUMPRODUCT((DATA!$A$2:$A$175=CONTROL!$C$6)*(DATA!$B$2:$B$175=2012)*INDEX(DATA!$C$2:$Q$175,0,MATCH(CONTROL!$C$8,DATA!$C$1:$Q$1,0))),"")
A10: 2013 | B10: =IFERROR(SUMPRODUCT((DATA!$A$2:$A$175=CONTROL!$C$6)*(DATA!$B$2:$B$175=2013)*INDEX(DATA!$C$2:$Q$175,0,MATCH(CONTROL!$C$8,DATA!$C$1:$Q$1,0))),"")
A11: 2014 | B11: =IFERROR(SUMPRODUCT((DATA!$A$2:$A$175=CONTROL!$C$6)*(DATA!$B$2:$B$175=2014)*INDEX(DATA!$C$2:$Q$175,0,MATCH(CONTROL!$C$8,DATA!$C$1:$Q$1,0))),"")
A12: 2015 | B12: =IFERROR(SUMPRODUCT((DATA!$A$2:$A$175=CONTROL!$C$6)*(DATA!$B$2:$B$175=2015)*INDEX(DATA!$C$2:$Q$175,0,MATCH(CONTROL!$C$8,DATA!$C$1:$Q$1,0))),"")
A13: 2016 | B13: =IFERROR(SUMPRODUCT((DATA!$A$2:$A$175=CONTROL!$C$6)*(DATA!$B$2:$B$175=2016)*INDEX(DATA!$C$2:$Q$175,0,MATCH(CONTROL!$C$8,DATA!$C$1:$Q$1,0))),"")
A14: 2017 | B14: =IFERROR(SUMPRODUCT((DATA!$A$2:$A$175=CONTROL!$C$6)*(DATA!$B$2:$B$175=2017)*INDEX(DATA!$C$2:$Q$175,0,MATCH(CONTROL!$C$8,DATA!$C$1:$Q$1,0))),"")
A15: 2018 | B15: =IFERROR(SUMPRODUCT((DATA!$A$2:$A$175=CONTROL!$C$6)*(DATA!$B$2:$B$175=2018)*INDEX(DATA!$C$2:$Q$175,0,MATCH(CONTROL!$C$8,DATA!$C$1:$Q$1,0))),"")
A16: 2019 | B16: =IFERROR(SUMPRODUCT((DATA!$A$2:$A$175=CONTROL!$C$6)*(DATA!$B$2:$B$175=2019)*INDEX(DATA!$C$2:$Q$175,0,MATCH(CONTROL!$C$8,DATA!$C$1:$Q$1,0))),"")
A17: 2020 | B17: =IFERROR(SUMPRODUCT((DATA!$A$2:$A$175=CONTROL!$C$6)*(DATA!$B$2:$B$175=2020)*INDEX(DATA!$C$2:$Q$175,0,MATCH(CONTROL!$C$8,DATA!$C$1:$Q$1,0))),"")
A18: 2021 | B18: =IFERROR(SUMPRODUCT((DATA!$A$2:$A$175=CONTROL!$C$6)*(DATA!$B$2:$B$175=2021)*INDEX(DATA!$C$2:$Q$175,0,MATCH(CONTROL!$C$8,DATA!$C$1:$Q$1,0))),"")
A19: 2022 | B19: =IFERROR(SUMPRODUCT((DATA!$A$2:$A$175=CONTROL!$C$6)*(DATA!$B$2:$B$175=2022)*INDEX(DATA!$C$2:$Q$175,0,MATCH(CONTROL!$C$8,DATA!$C$1:$Q$1,0))),"")
A20: 2023 | B20: =IFERROR(SUMPRODUCT((DATA!$A$2:$A$175=CONTROL!$C$6)*(DATA!$B$2:$B$175=2023)*INDEX(DATA!$C$2:$Q$175,0,MATCH(CONTROL!$C$8,DATA!$C$1:$Q$1,0))),"")
A21: 2024 | B21: =IFERROR(SUMPRODUCT((DATA!$A$2:$A$175=CONTROL!$C$6)*(DATA!$B$2:$B$175=2024)*INDEX(DATA!$C$2:$Q$175,0,MATCH(CONTROL!$C$8,DATA!$C$1:$Q$1,0))),"")
A22: 2025 | B22: =IFERROR(SUMPRODUCT((DATA!$A$2:$A$175=CONTROL!$C$6)*(DATA!$B$2:$B$175=2025)*INDEX(DATA!$C$2:$Q$175,0,MATCH(CONTROL!$C$8,DATA!$C$1:$Q$1,0))),"")
A23: 2026 | B23: =IFERROR(SUMPRODUCT((DATA!$A$2:$A$175=CONTROL!$C$6)*(DATA!$B$2:$B$175=2026)*INDEX(DATA!$C$2:$Q$175,0,MATCH(CONTROL!$C$8,DATA!$C$1:$Q$1,0))),"")

Sheet ACROSS_SECTORS
A1: Sector Medians — Cross-Sectional Snapshot
A3: → Change selections on CONTROL sheet to update this chart
A4: Year: | B4: =CONTROL!G6 | C4: Metric: | D4: =CONTROL!G8
A7: Sector | B7: Value
A8: Basic Materials | B8: =IFERROR(SUMPRODUCT((DATA!$A$2:$A$175="Basic Materials")*(DATA!$B$2:$B$175=VALUE(CONTROL!$G$6))*INDEX(DATA!$C$2:$Q$175,0,MATCH(CONTROL!$G$8,DATA!$C$1:$Q$1,0))),"")
A9: Communication Services | B9: =IFERROR(SUMPRODUCT((DATA!$A$2:$A$175="Communication Services")*(DATA!$B$2:$B$175=VALUE(CONTROL!$G$6))*INDEX(DATA!$C$2:$Q$175,0,MATCH(CONTROL!$G$8,DATA!$C$1:$Q$1,0))),"")
A10: Consumer Cyclical | B10: =IFERROR(SUMPRODUCT((DATA!$A$2:$A$175="Consumer Cyclical")*(DATA!$B$2:$B$175=VALUE(CONTROL!$G$6))*INDEX(DATA!$C$2:$Q$175,0,MATCH(CONTROL!$G$8,DATA!$C$1:$Q$1,0))),"")
A11: Consumer Defensive | B11: =IFERROR(SUMPRODUCT((DATA!$A$2:$A$175="Consumer Defensive")*(DATA!$B$2:$B$175=VALUE(CONTROL!$G$6))*INDEX(DATA!$C$2:$Q$175,0,MATCH(CONTROL!$G$8,DATA!$C$1:$Q$1,0))),"")
A12: Energy | B12: =IFERROR(SUMPRODUCT((DATA!$A$2:$A$175="Energy")*(DATA!$B$2:$B$175=VALUE(CONTROL!$G$6))*INDEX(DATA!$C$2:$Q$175,0,MATCH(CONTROL!$G$8,DATA!$C$1:$Q$1,0))),"")
A13: Financial Services | B13: =IFERROR(SUMPRODUCT((DATA!$A$2:$A$175="Financial Services")*(DATA!$B$2:$B$175=VALUE(CONTROL!$G$6))*INDEX(DATA!$C$2:$Q$175,0,MATCH(CONTROL!$G$8,DATA!$C$1:$Q$1,0))),"")
A14: Healthcare | B14: =IFERROR(SUMPRODUCT((DATA!$A$2:$A$175="Healthcare")*(DATA!$B$2:$B$175=VALUE(CONTROL!$G$6))*INDEX(DATA!$C$2:$Q$175,0,MATCH(CONTROL!$G$8,DATA!$C$1:$Q$1,0))),"")
A15: Industrials | B15: =IFERROR(SUMPRODUCT((DATA!$A$2:$A$175="Industrials")*(DATA!$B$2:$B$175=VALUE(CONTROL!$G$6))*INDEX(DATA!$C$2:$Q$175,0,MATCH(CONTROL!$G$8,DATA!$C$1:$Q$1,0))),"")
A16: Real Estate | B16: =IFERROR(SUMPRODUCT((DATA!$A$2:$A$175="Real Estate")*(DATA!$B$2:$B$175=VALUE(CONTROL!$G$6))*INDEX(DATA!$C$2:$Q$175,0,MATCH(CONTROL!$G$8,DATA!$C$1:$Q$1,0))),"")
A17: Technology | B17: =IFERROR(SUMPRODUCT((DATA!$A$2:$A$175="Technology")*(DATA!$B$2:$B$175=VALUE(CONTROL!$G$6))*INDEX(DATA!$C$2:$Q$175,0,MATCH(CONTROL!$G$8,DATA!$C$1:$Q$1,0))),"")
A18: Utilities | B18: =IFERROR(SUMPRODUCT((DATA!$A$2:$A$175="Utilities")*(DATA!$B$2:$B$175=VALUE(CONTROL!$G$6))*INDEX(DATA!$C$2:$Q$175,0,MATCH(CONTROL!$G$8,DATA!$C$1:$Q$1,0))),"")
